chatterbox/__init__.py
chatterbox/__main__.py
chatterbox/cli.py
chatterbox/generation_utils.py
chatterbox/mtl_tts.py
chatterbox/mtl_tts_mlx.py
chatterbox/tts.py
chatterbox/tts_mlx.py
chatterbox/vc.py
chatterbox/models/__init__.py
chatterbox/models/utils.py
chatterbox/models/s3gen/__init__.py
chatterbox/models/s3gen/configs.py
chatterbox/models/s3gen/const.py
chatterbox/models/s3gen/decoder.py
chatterbox/models/s3gen/f0_predictor.py
chatterbox/models/s3gen/flow.py
chatterbox/models/s3gen/flow_matching.py
chatterbox/models/s3gen/hifigan.py
chatterbox/models/s3gen/s3gen.py
chatterbox/models/s3gen/xvector.py
chatterbox/models/s3gen/matcha/decoder.py
chatterbox/models/s3gen/matcha/flow_matching.py
chatterbox/models/s3gen/matcha/text_encoder.py
chatterbox/models/s3gen/matcha/transformer.py
chatterbox/models/s3gen/transformer/__init__.py
chatterbox/models/s3gen/transformer/activation.py
chatterbox/models/s3gen/transformer/attention.py
chatterbox/models/s3gen/transformer/convolution.py
chatterbox/models/s3gen/transformer/embedding.py
chatterbox/models/s3gen/transformer/encoder_layer.py
chatterbox/models/s3gen/transformer/positionwise_feed_forward.py
chatterbox/models/s3gen/transformer/subsampling.py
chatterbox/models/s3gen/transformer/upsample_encoder.py
chatterbox/models/s3gen/utils/class_utils.py
chatterbox/models/s3gen/utils/mask.py
chatterbox/models/s3gen/utils/mel.py
chatterbox/models/s3gen_mlx/__init__.py
chatterbox/models/s3gen_mlx/convert_weights.py
chatterbox/models/s3gen_mlx/decoder_mlx.py
chatterbox/models/s3gen_mlx/f0_predictor_mlx.py
chatterbox/models/s3gen_mlx/flow_matching_mlx.py
chatterbox/models/s3gen_mlx/flow_mlx.py
chatterbox/models/s3gen_mlx/hifigan_mlx.py
chatterbox/models/s3gen_mlx/s3gen_mlx.py
chatterbox/models/s3gen_mlx/xvector_mlx.py
chatterbox/models/s3gen_mlx/matcha/__init__.py
chatterbox/models/s3gen_mlx/matcha/decoder_mlx.py
chatterbox/models/s3gen_mlx/matcha/transformer_mlx.py
chatterbox/models/s3gen_mlx/transformer/__init__.py
chatterbox_mlx-1.0.4.dist-info/licenses/LICENSE
chatterbox_mlx-1.0.4.dist-info/METADATA
chatterbox_mlx-1.0.4.dist-info/WHEEL
chatterbox_mlx-1.0.4.dist-info/entry_points.txt
chatterbox_mlx-1.0.4.dist-info/top_level.txt
chatterbox_mlx-1.0.4.dist-info/RECORD
