Metadata-Version: 2.4
Name: chatterbox-mlx
Version: 1.0.4
Summary: Chatterbox MLX: Open Source TTS and Voice Conversion for MLX. Based off of Chatterbox by Resemble AI
Author-email: michael-yang <contact@michaelyang.ai>
License-Expression: MIT
Project-URL: Homepage, https://github.com/michaelcreatesstuff/chatterbox
Project-URL: Repository, https://github.com/michaelcreatesstuff/chatterbox
Keywords: tts,text-to-speech,voice-cloning,speech-synthesis,ai,multilingual,mlx,apple-silicon
Classifier: Development Status :: 4 - Beta
Classifier: Intended Audience :: Developers
Classifier: Intended Audience :: Science/Research
Classifier: Programming Language :: Python :: 3
Classifier: Programming Language :: Python :: 3.11
Classifier: Programming Language :: Python :: 3.12
Classifier: Topic :: Multimedia :: Sound/Audio :: Speech
Classifier: Topic :: Scientific/Engineering :: Artificial Intelligence
Requires-Python: <3.13,>=3.11
License-File: LICENSE
Requires-Dist: numpy==2.3.5
Requires-Dist: scipy>=1.11.0
Requires-Dist: librosa==0.11.0
Requires-Dist: s3tokenizer
Requires-Dist: torch==2.8.0
Requires-Dist: torchaudio==2.8.0
Requires-Dist: torchcodec>=0.7.0
Requires-Dist: transformers==4.57.3
Requires-Dist: diffusers==0.35.2
Requires-Dist: resemble-perth==1.0.1
Requires-Dist: conformer==0.3.2
Requires-Dist: safetensors>=0.7.0
Requires-Dist: huggingface-hub>=0.20.0
Requires-Dist: spacy>=3.8.3
Requires-Dist: spacy-pkuseg==1.0.1
Requires-Dist: pykakasi==2.3.0
Requires-Dist: psutil==7.2.0
Requires-Dist: mlx==0.30.1
Requires-Dist: mlx-lm==0.28.3
Provides-Extra: dev
Requires-Dist: mlx-whisper>=0.4.0; extra == "dev"
Requires-Dist: parakeet-mlx==0.4.1; extra == "dev"
Requires-Dist: black==25.12.0; extra == "dev"
Requires-Dist: ruff==0.14.10; extra == "dev"
Requires-Dist: pytest==9.0.2; extra == "dev"
Requires-Dist: build==1.3.0; extra == "dev"
Requires-Dist: twine==6.2.0; extra == "dev"
Dynamic: license-file
